pydemux/__init__.py
pydemux/argparser.py
pydemux/core.py
pydemux/pydemux.py
pydemux/utils.py
pydemux-1.0.1.dist-info/LICENSE
pydemux-1.0.1.dist-info/METADATA
pydemux-1.0.1.dist-info/WHEEL
pydemux-1.0.1.dist-info/entry_points.txt
pydemux-1.0.1.dist-info/top_level.txt
pydemux-1.0.1.dist-info/RECORD
