Metadata-Version: 2.1
Name: pydemux
Version: 1.0.1
Summary: Python package for demultiplexing raw sequencing reads in SAM/BAM format
Author-email: Daniel Malzl <daniel@menchelab.com>
License: MIT License        
Project-URL: Homepage, https://github.com/dmalzl/pydemux
Keywords: squencing,ngs,demultiplexing,bam,sam
Classifier: License :: OSI Approved :: MIT License
Classifier: Programming Language :: Python
Classifier: Programming Language :: Python :: 3
Requires-Python: >=3.9
License-File: LICENSE
Requires-Dist: pysam (>=0.19.1)
Requires-Dist: regex (>=2.5.121)
